contractor/__init__.py
contractor/admin.py
contractor/apps.py
contractor/cms_models.py
contractor/cms_plugins.py
contractor/models.py
contractor/tasks.py
contractor/urls.py
contractor/utils.py
contractor/views.py
contractor/migrations/0001_initial.py
contractor/migrations/0002_contract_webhook_active.py
contractor/migrations/__init__.py
contractor/templates/admin/contractor/contract/change_form.html
contractor/templates/contractor/render.html
django_contractor-0.0.8.dist-info/LICENSE
django_contractor-0.0.8.dist-info/METADATA
django_contractor-0.0.8.dist-info/WHEEL
django_contractor-0.0.8.dist-info/top_level.txt
django_contractor-0.0.8.dist-info/RECORD
